npr_news_now_cli/__init__.py
npr_news_now_cli/listen.py
npr_news_now_cli-0.1.2.dist-info/LICENSE
npr_news_now_cli-0.1.2.dist-info/METADATA
npr_news_now_cli-0.1.2.dist-info/WHEEL
npr_news_now_cli-0.1.2.dist-info/entry_points.txt
npr_news_now_cli-0.1.2.dist-info/top_level.txt
npr_news_now_cli-0.1.2.dist-info/RECORD
