Metadata-Version: 2.1
Name: npr-news-now-cli
Version: 0.1.2
Summary: A command-line tool to listen to the latest NPR news now hourly news update.
Home-page: https://github.com/alexpgates/npr-news-now-cli
Author: Alex P. Gates
Author-email: alexpgates@gmail.com
Classifier: Programming Language :: Python :: 3
Classifier: License :: OSI Approved :: MIT License
Classifier: Operating System :: OS Independent
Requires-Python: >=3.6
License-File: LICENSE
Requires-Dist: feedparser
